{"exportServer":false,"exportClient":true,"exportJson":false,"json_merge":false,"json_all_cfg_file_name":"GameJsonCfg","json_format":false,"json_save_path":"","json_import_project_cfg_path":"","ts_save_path":"L:\\LazyFishKing\\LazyFishKing\\assets\\scripts\\data","ts_merge":true,"ts_file_name":"GameTsCfg","exportTs":true,"exportJs":false,"js_save_path":"","js_merge":false,"js_file_name":"GameJsCfg","js_format":false,"exportLua":false,"excel_root_path":"J:\\Download\\excel","expand_excel":true,"expand_json":false,"expand_js":false,"expand_ts":true,"expand_lua":true,"expand_export":true}